rpi5powermonitor/__init__.py
rpi5powermonitor/cli.py
rpi5powermonitor-0.2.0.dist-info/WHEEL
rpi5powermonitor-0.2.0.dist-info/entry_points.txt
rpi5powermonitor-0.2.0.dist-info/METADATA
rpi5powermonitor-0.2.0.dist-info/RECORD
