Metadata-Version: 2.3
Name: rpi5powermonitor
Version: 0.2.0
Summary: Power Monitoring CLI Tool for Raspberry Pi 5+
Author: DiamondGotCat
Author-email: DiamondGotCat <nercone@diamondgotcat.net>
License: MIT
Classifier: Programming Language :: Python :: 3
Classifier: License :: OSI Approved :: MIT License
Classifier: Operating System :: POSIX :: Linux
Requires-Dist: rich
Requires-Python: >=3.9
